{
    "data": [
        {
            "buying": [
                {
                    "id": 1,
                    "title": " عقد بيع شقة ",
                    "image": "https://i.suar.me/jyO0m/l",
                    "text": [
                        { 
                            "-": "إنه في يوم ــــــــــــ الموافق ــــــــــــ \n تحرر هذا العقد بين كل من: \n أولًا: السيد/ ………………………………………………..، ويحمل بطاقة رقم قومي/ ………………………………، ومقيم في/ …………………………………………………  (طرف أول بائع) \n ثانيًا: السيد/ ………………………………………………..، ويحمل بطاقة رقم قومي/ ………………………………، ومقيم في/ ………………………………………………… .   (طرف ثانٍ مشترٍ) \n : أقر كلا الطرفين بأهليتهما، واتفقا فيما بينهما على ما يأتي"
                        },
                        { 
                            "البند الأول": "باع وأسقط وتنازل بكافة الضمانات الفعلية والقانونية الطرف الأول إلى الطرف الثاني ما هو عبارة عن الشقة رقم (…….) بالدور ………….. والكائنة بالعمارة ………….. وتبلغ مساحتها ………….. متر مربع، والشقة مكونة من …………………………. . \n والوحدة السكنية موضوع العقد محددة بالحدود الآتية: \n الحد البحري: \n الحد الشرقي:  \n الحد الغربي: \n الحد القبلي: "
                        },
                        { 
                            "البند الثاني": "تم هذا البيع نظير مبلغ إجمالي وقدره ……………….. جنيه مصري، تم دفع كامل المبلغ وذلك عند تحرير هذا العقد، ويعتبر توقيع الطرف الأول على هذا العقد بمثابة مخالصة تامة ونهائية باستلامه وقبضه كامل ثمن البيع، وأصبح هذا العقد عقد بيع نهائي خالص الثمن، ولا توجد مبالغ أخرى للطرف الأول لدى الطرف الثاني، ولا يحق له مطالبته بأية مبالغ أخرى فيما بعد بخلاف ما ذكر بذلك البند."
                        },
                        { 
                            "البند الثالث": "يقر الطرف الأول البائع بأن العقار المبيع وموضوع الحصة المبيعة آلت إليه بموجب العقد المسجل رقم ………. لسنة ………. شهر عقاري ………. محافظة ………. كما يقر البائع بأن ملكية الحصة المبيعة  من ماله الخاص."
                        },
                        { 
                            "البند الرابع": "يقر الطرف الثاني أنه عاين الشقة موضوع هذا العقد المعاينة التامة النافية للجهالة شرعًا وقانونًا، وأنه قبلها على حالتها التي هي عليها الآن."
                        },
                        { 
                            "البند الخامس": "يقر الطرف الأول بأنه لم يسبق له التصرف في الوحدة المباعة موضوع هذا العقد بأي نوع من أنواع التصرفات الناقلة والمكسبة للملكية لها، وأن الوحدة السكنية خالية تمامًا من كافة الحقوق العينية الأصلية منها التبعية كالرهن والاختصاص والامتياز وحقوق الارتفاق ظاهرة كانت أم خفية. ويضمن الطرف الأول عدم تعرضه للطرف الثاني أو تعرض الغير له في حيازة وملكية الطرف الثاني للوحدة موضوع العقد."
                        },
                        { 
                            "البند السادس": "يقر الطرف الأول بأن الشقة المباعة خالية من جميع الديون والرهون وكافة الحقوق العينية."
                        },
                        { 
                            "البند السابع": "يقر الطرف الأول بأن يتم تسليم الوحدة السكنية وذلك في موعد أقصاه فور التوقيع على هذا العقد، ويقر الطرف الثاني بأنه استلم الوحدة السكنية  فور التوقيع على العقد وتسلمها الطرف الثاني."
                        },
                        { 
                            "البند الثامن": "يقر الطرف الأول (البائع) بتسليم كافة صور مستندات ملكية العين موضوع العقد للطرف الثاني (المشتري)، وأقر الطرف الثاني (المشتري) بأنه تسلم كافة صور هذه المستندات."
                        },
                        { 
                            "البند التاسع": "تختص جميع محاكم القاهرة الكلية والجزئية بنظر أي نزاع قد ينشأ بخصوص تنفيذ هذا العقد أو تفسير أي بند من بنوده."
                        },
                        { 
                            "البند العاشر": "تحرر هذا العقد من نسختين، بيد كل طرف نسخة للعمل بها عند اللزوم."
                        },
                        { 
                            "توقيعات": "الطرف الأول (البائع)                                                     الطرف الثاني (المشتري)\n\nالاسم/ ………………………………………………… الاسم/ …………………………………………………\n\nالرقم القومي/ ………………………………………….. الرقم القومي/ …………………………………………. "
                        }
                    ]
                },
                {
                    "id": 2,
                    "title": " عقد بيع ارض ",
                    "image": "https://i.suar.me/jyO0m/l",
                    "text": [
                        { 
                            "-": "إنه في يوم ــــــــــــ الموافق ــــــــــــ \n تحرر هذا العقد بين كل من: \n أولًا: السيد/ ………………………………………………..، ويحمل بطاقة رقم قومي/ ………………………………، ومقيم في/ …………………………………………………  (طرف أول بائع) \n ثانيًا: السيد/ ………………………………………………..، ويحمل بطاقة رقم قومي/ ………………………………، ومقيم في/ ………………………………………………… .   (طرف ثانٍ مشترٍ) \n : أقر كلا الطرفين بأهليتهما، واتفقا فيما بينهما على ما يأتي"
                        },
                        { 
                            "البند الأول": "باع وأسقط وتنازل بكافة الضمانات الفعلية والقانونية الطرف الأول إلى الطرف الثاني ما هو عبارة عن قطعة ارض الكائنة فى ............... و تبلغ مساحتها ...........  …………………………. . \n والارض المبيعة موضوع العقد محددة بالحدود الآتية: \n الحد البحري: \n الحد الشرقي:  \n الحد الغربي: \n الحد القبلي: "
                        },
                        { 
                            "البند الثاني": "تم هذا البيع نظير مبلغ إجمالي وقدره ……………….. جنيه مصري، تم دفع كامل المبلغ وذلك عند تحرير هذا العقد، ويعتبر توقيع الطرف الأول على هذا العقد بمثابة مخالصة تامة ونهائية باستلامه وقبضه كامل ثمن البيع، وأصبح هذا العقد عقد بيع نهائي خالص الثمن، ولا توجد مبالغ أخرى للطرف الأول لدى الطرف الثاني، ولا يحق له مطالبته بأية مبالغ أخرى فيما بعد بخلاف ما ذكر بذلك البند."
                        },
                        { 
                            "البند الثالث": "يقر الطرف الأول البائع بأن العقار المبيع وموضوع الحصة المبيعة آلت إليه بموجب العقد المسجل رقم ………. لسنة ………. شهر عقاري ………. محافظة ………. كما يقر البائع بأن ملكية الحصة المبيعة  من ماله الخاص."
                        },
                        { 
                            "البند الرابع": "يقر الطرف الثاني أنه عاين الشقة موضوع هذا العقد المعاينة التامة النافية للجهالة شرعًا وقانونًا، وأنه قبلها على حالتها التي هي عليها الآن."
                        },
                        { 
                            "البند الخامس": "يقر الطرف الأول بأنه لم يسبق له التصرف في الوحدة المباعة موضوع هذا العقد بأي نوع من أنواع التصرفات الناقلة والمكسبة للملكية لها، وأن الوحدة السكنية خالية تمامًا من كافة الحقوق العينية الأصلية منها التبعية كالرهن والاختصاص والامتياز وحقوق الارتفاق ظاهرة كانت أم خفية. ويضمن الطرف الأول عدم تعرضه للطرف الثاني أو تعرض الغير له في حيازة وملكية الطرف الثاني للوحدة موضوع العقد."
                        },
                        { 
                            "البند السادس": "يقر الطرف الأول بأن الشقة المباعة خالية من جميع الديون والرهون وكافة الحقوق العينية."
                        },
                        { 
                            "البند السابع": "يقر الطرف الأول بأن يتم تسليم الوحدة السكنية وذلك في موعد أقصاه فور التوقيع على هذا العقد، ويقر الطرف الثاني بأنه استلم الوحدة السكنية  فور التوقيع على العقد وتسلمها الطرف الثاني."
                        },
                        { 
                            "البند الثامن": "يقر الطرف الأول (البائع) بتسليم كافة صور مستندات ملكية العين موضوع العقد للطرف الثاني (المشتري)، وأقر الطرف الثاني (المشتري) بأنه تسلم كافة صور هذه المستندات."
                        },
                        { 
                            "البند التاسع": "تختص جميع محاكم القاهرة الكلية والجزئية بنظر أي نزاع قد ينشأ بخصوص تنفيذ هذا العقد أو تفسير أي بند من بنوده."
                        },
                        { 
                            "البند العاشر": "تحرر هذا العقد من نسختين، بيد كل طرف نسخة للعمل بها عند اللزوم."
                        },
                        { 
                            "توقيعات": "الطرف الأول (البائع)                                                     الطرف الثاني (المشتري)\n\nالاسم/ ………………………………………………… الاسم/ …………………………………………………\n\nالرقم القومي/ ………………………………………….. الرقم القومي/ …………………………………………. "
                        }
                    ]
                },
                {
                    "id": 3,
                    "title": " عقد بيع محل ",
                    "image": "https://i.suar.me/jyO0m/l",
                    "text": [
                        { 
                            "-": "إنه في يوم ــــــــــــ الموافق ــــــــــــ \n تحرر هذا العقد بين كل من: \n أولًا: السيد/ ………………………………………………..، ويحمل بطاقة رقم قومي/ ………………………………، ومقيم في/ …………………………………………………  (طرف أول بائع) \n ثانيًا: السيد/ ………………………………………………..، ويحمل بطاقة رقم قومي/ ………………………………، ومقيم في/ ………………………………………………… .   (طرف ثانٍ مشترٍ) \n : أقر كلا الطرفين بأهليتهما، واتفقا فيما بينهما على ما يأتي"
                        },
                        { 
                            "البند الأول": "باع وأسقط وتنازل بكافة الضمانات الفعلية والقانونية الطرف الأول إلى الطرف الثاني ما هو عبارة عن الشقة رقم (…….) بالدور ………….. والكائنة بالعمارة ………….. وتبلغ مساحتها ………….. متر مربع، والشقة مكونة من …………………………. . \n والوحدة السكنية موضوع العقد محددة بالحدود الآتية: \n الحد البحري: \n الحد الشرقي:  \n الحد الغربي: \n الحد القبلي: "
                        },
                        { 
                            "البند الثاني": "تم هذا البيع نظير مبلغ إجمالي وقدره ……………….. جنيه مصري، تم دفع كامل المبلغ وذلك عند تحرير هذا العقد، ويعتبر توقيع الطرف الأول على هذا العقد بمثابة مخالصة تامة ونهائية باستلامه وقبضه كامل ثمن البيع، وأصبح هذا العقد عقد بيع نهائي خالص الثمن، ولا توجد مبالغ أخرى للطرف الأول لدى الطرف الثاني، ولا يحق له مطالبته بأية مبالغ أخرى فيما بعد بخلاف ما ذكر بذلك البند."
                        },
                        { 
                            "البند الثالث": "يقر الطرف الأول البائع بأن العقار المبيع وموضوع الحصة المبيعة آلت إليه بموجب العقد المسجل رقم ………. لسنة ………. شهر عقاري ………. محافظة ………. كما يقر البائع بأن ملكية الحصة المبيعة  من ماله الخاص."
                        },
                        { 
                            "البند الرابع": "يقر الطرف الثاني أنه عاين الشقة موضوع هذا العقد المعاينة التامة النافية للجهالة شرعًا وقانونًا، وأنه قبلها على حالتها التي هي عليها الآن."
                        },
                        { 
                            "البند الخامس": "يقر الطرف الأول بأنه لم يسبق له التصرف في الوحدة المباعة موضوع هذا العقد بأي نوع من أنواع التصرفات الناقلة والمكسبة للملكية لها، وأن الوحدة السكنية خالية تمامًا من كافة الحقوق العينية الأصلية منها التبعية كالرهن والاختصاص والامتياز وحقوق الارتفاق ظاهرة كانت أم خفية. ويضمن الطرف الأول عدم تعرضه للطرف الثاني أو تعرض الغير له في حيازة وملكية الطرف الثاني للوحدة موضوع العقد."
                        },
                        { 
                            "البند السادس": "يقر الطرف الأول بأن الشقة المباعة خالية من جميع الديون والرهون وكافة الحقوق العينية."
                        },
                        { 
                            "البند السابع": "يقر الطرف الأول بأن يتم تسليم الوحدة السكنية وذلك في موعد أقصاه فور التوقيع على هذا العقد، ويقر الطرف الثاني بأنه استلم الوحدة السكنية  فور التوقيع على العقد وتسلمها الطرف الثاني."
                        },
                        { 
                            "البند الثامن": "يقر الطرف الأول (البائع) بتسليم كافة صور مستندات ملكية العين موضوع العقد للطرف الثاني (المشتري)، وأقر الطرف الثاني (المشتري) بأنه تسلم كافة صور هذه المستندات."
                        },
                        { 
                            "البند التاسع": "تختص جميع محاكم القاهرة الكلية والجزئية بنظر أي نزاع قد ينشأ بخصوص تنفيذ هذا العقد أو تفسير أي بند من بنوده."
                        },
                        { 
                            "البند العاشر": "تحرر هذا العقد من نسختين، بيد كل طرف نسخة للعمل بها عند اللزوم."
                        },
                        { 
                            "توقيعات": "الطرف الأول (البائع)                                                     الطرف الثاني (المشتري)\n\nالاسم/ ………………………………………………… الاسم/ …………………………………………………\n\nالرقم القومي/ ………………………………………….. الرقم القومي/ …………………………………………. "
                        }
                    ]
                }
            ]
        }
    ]
}